LICENSE
MANIFEST.in
README.rst
VERSION
setup.py
jubatus/__init__.py
jubatus/embedded.py
jubatus.egg-info/PKG-INFO
jubatus.egg-info/SOURCES.txt
jubatus.egg-info/dependency_links.txt
jubatus.egg-info/requires.txt
jubatus.egg-info/top_level.txt
jubatus/anomaly/__init__.py
jubatus/anomaly/client.py
jubatus/anomaly/types.py
jubatus/bandit/__init__.py
jubatus/bandit/client.py
jubatus/bandit/types.py
jubatus/burst/__init__.py
jubatus/burst/client.py
jubatus/burst/types.py
jubatus/classifier/__init__.py
jubatus/classifier/client.py
jubatus/classifier/types.py
jubatus/clustering/__init__.py
jubatus/clustering/client.py
jubatus/clustering/types.py
jubatus/common/__init__.py
jubatus/common/client.py
jubatus/common/compat.py
jubatus/common/datum.py
jubatus/common/message_string_generator.py
jubatus/common/types.py
jubatus/graph/__init__.py
jubatus/graph/client.py
jubatus/graph/types.py
jubatus/nearest_neighbor/__init__.py
jubatus/nearest_neighbor/client.py
jubatus/nearest_neighbor/types.py
jubatus/recommender/__init__.py
jubatus/recommender/client.py
jubatus/recommender/types.py
jubatus/regression/__init__.py
jubatus/regression/client.py
jubatus/regression/types.py
jubatus/stat/__init__.py
jubatus/stat/client.py
jubatus/stat/types.py
jubatus/weight/__init__.py
jubatus/weight/client.py
jubatus/weight/types.py
test/jubatus_test/__init__.py
test/jubatus_test/test_util.py
test/jubatus_test/anomaly/__init__.py
test/jubatus_test/anomaly/test.py
test/jubatus_test/classifier/__init__.py
test/jubatus_test/classifier/test.py
test/jubatus_test/clustering/__init__.py
test/jubatus_test/clustering/test.py
test/jubatus_test/common/__init__.py
test/jubatus_test/common/test_client.py
test/jubatus_test/common/test_datum.py
test/jubatus_test/common/test_message_string_generator.py
test/jubatus_test/common/test_types.py
test/jubatus_test/error/__init__.py
test/jubatus_test/error/test.py
test/jubatus_test/graph/__init__.py
test/jubatus_test/graph/test.py
test/jubatus_test/nearest_neighbor/__init__.py
test/jubatus_test/nearest_neighbor/test.py
test/jubatus_test/recommender/__init__.py
test/jubatus_test/recommender/test.py
