Metadata-Version: 1.1
Name: jubatus
Version: 1.0.2
Summary: Jubatus is a distributed processing framework and streaming machine learning library. This is the Jubatus client in Python.
Home-page: http://jubat.us
Author: PFN & NTT
Author-email: jubatus-team@googlegroups.com
License: MIT License
Download-URL: http://pypi.python.org/pypi/jubatus/
Platform: Linux
Classifier: Development Status :: 5 - Production/Stable
Classifier: Intended Audience :: Developers
Classifier: Intended Audience :: Science/Research
Classifier: License :: OSI Approved :: MIT License
Classifier: Programming Language :: Python
Classifier: Programming Language :: Python :: 2
Classifier: Programming Language :: Python :: 2.6
Classifier: Programming Language :: Python :: 2.7
Classifier: Programming Language :: Python :: 3
Classifier: Programming Language :: Python :: 3.3
Classifier: Programming Language :: Python :: 3.4
Classifier: Programming Language :: Python :: 3.5
Classifier: Topic :: Scientific/Engineering :: Information Analysis
